ipyleaflet/__init__.py
ipyleaflet/_version.py
ipyleaflet/basemaps.py
ipyleaflet/leaflet.py
ipyleaflet/projections.py
ipyleaflet/velocity.py
ipyleaflet/xarray_ds.py
ipyleaflet/external/__init__.py
ipyleaflet/external/here.py
ipyleaflet/labextension/package.json
ipyleaflet/labextension/static/00179c4c1ee830d3a108.png
ipyleaflet/labextension/static/0194f340b27a4c5be35b.png
ipyleaflet/labextension/static/066daca850d8ffbef007.png
ipyleaflet/labextension/static/138.d76a33f1d3263aaa60fc.js
ipyleaflet/labextension/static/1755d22b1ffb0e8589b2.png
ipyleaflet/labextension/static/1d58b682e64eeac7a47f.png
ipyleaflet/labextension/static/1dbbe9d028e292f36fcb.png
ipyleaflet/labextension/static/243.45f065b556905df86ca2.js
ipyleaflet/labextension/static/243.45f065b556905df86ca2.js.LICENSE.txt
ipyleaflet/labextension/static/264f5c640339f042dd72.png
ipyleaflet/labextension/static/292.4107fc80f490ac63e379.js
ipyleaflet/labextension/static/2972e9515ff9b486d358.png
ipyleaflet/labextension/static/35.eb4b6d6bf1ffeee78ab0.js
ipyleaflet/labextension/static/366.a7b543196042a69b6553.js
ipyleaflet/labextension/static/408.2d9f0740a6db65f5d011.js
ipyleaflet/labextension/static/40bb0aff173baa6b3e8d.png
ipyleaflet/labextension/static/52aceec684de337b9359.png
ipyleaflet/labextension/static/550.d5d4cff7dfc1cd2c5db9.js
ipyleaflet/labextension/static/558233345e005b15b6b8.png
ipyleaflet/labextension/static/574c3a5cca85f4114085.png
ipyleaflet/labextension/static/5d55e5b00993a8a670e7.png
ipyleaflet/labextension/static/665.5238b4be159a24e206a7.js
ipyleaflet/labextension/static/687.6c0a27b7c659dcc31c14.js
ipyleaflet/labextension/static/691.4209e85da8c2f25ef40a.js
ipyleaflet/labextension/static/7107fd0636a571de7207.png
ipyleaflet/labextension/static/732.755ed92c4bd1cc1f291b.js
ipyleaflet/labextension/static/738.3cb98a41cc77eed3dc2d.js
ipyleaflet/labextension/static/751.ccc2a387c69ff1829bef.js
ipyleaflet/labextension/static/787.6c817ebd9f207c63c60f.js
ipyleaflet/labextension/static/795.ce5445668429487f077e.js
ipyleaflet-0.18.2.dist-info/LICENSE
ipyleaflet-0.18.2.dist-info/METADATA
ipyleaflet-0.18.2.dist-info/WHEEL
ipyleaflet-0.18.2.dist-info/top_level.txt
ipyleaflet-0.18.2.dist-info/RECORD
